is_uv_demo/__init__.py
is_uv_demo/demo_stats.py
is_uv_demo-1.0.0.dist-info/WHEEL
is_uv_demo-1.0.0.dist-info/entry_points.txt
is_uv_demo-1.0.0.dist-info/METADATA
is_uv_demo-1.0.0.dist-info/RECORD
