Metadata-Version: 2.3
Name: is-uv-demo
Version: 1.0.0
Summary: Add your description here
Author: Isaac Spackman
Author-email: Isaac Spackman <isaacjspackman@gmail.com>
Requires-Dist: scipy>=1.16.2
Requires-Python: >=3.13
